lzmp.py
lzmp_test.py
lzmp-0.3.1.dist-info/METADATA
lzmp-0.3.1.dist-info/WHEEL
lzmp-0.3.1.dist-info/entry_points.txt
lzmp-0.3.1.dist-info/top_level.txt
lzmp-0.3.1.dist-info/RECORD
