Metadata-Version: 2.1
Name: lzmp
Version: 0.3.1
Summary: simple wrapper around the multiprocessing module allowing the lazy programmer to run batches of processes
Author-email: Stéphane De Mita <demita@gmail.com>
Project-URL: Homepage, https://gitlab.com/demita/lzmp
Project-URL: Documentation, https://lzmp.readthedocs.io/en/latest/
Classifier: Programming Language :: Python :: 3
Classifier: License :: OSI Approved :: GNU General Public License v3 or later (GPLv3+)
Classifier: Operating System :: OS Independent
Requires-Python: >=3.7
